{"personSlug":"chandra-janakiraman","personName":"Chandra Janakiraman","chunkIndex":1,"sourceTitle":"An operator’s guide to product strategy | Chandra Janakiraman (CPO at VRChat, ex-Meta, Headspace, Zynga)","sourceType":"podcast","sourceDate":"2025-01-26","text":"scan the historical archives at the company and sort of synthesize and condense that into a very sort of digestible macro themes and learnings about users. So that's sort of one preparation phase item. (00:21:16): The second is UXR insight. So again, there's probably a lot of soft hard signals about users, not just based on research that's run by user researchers, but also potentially from the customer service team, social channels, and basically a meta analysis of all of that into one very actionable and synthesized deck on all the insights on users. That's usually led by the design person and with support from their research team. And that's sort of the second action item. (00:21:53): The third action item is leadership interviews. So I sort of have this fun story of the fruit with leadership strategy reviews, which I want to share. So imagine, this is sort of how sometimes strategy reviews go, which is you bring a fruit to the reviewer and say, \"Hey, here's a mango, what do you think?\" And the reviewer says, \"I actually don't like mangoes.\" And you're like, \"Oh,\" you're sort of sad. You take it back, you bring an apple and you show, \"Hey, what do you think of an apple?\" And then the leader says, \"I actually stopped eating apples last year.\" And so you're disappointed again. You go back, you bring a banana. \"I hated bananas since I was a kid.\" And so it's a bit of a silly caricature of reviews, but there's a bit of grain of truth there, which is, imagine how frustrating that is for both the reviewer and the person who's reviewing. (00:22:54): And so it could be made so much better if you just engage with your leaders before you actually build a strategy. It's amazing how few people actually do that. And so the fruit story tells you, hey, imagine if you just asked the reviewer, \"Do you even like fruits?\" How much better the experience would've been for both parties. And so leadership interviews are a very important part of a strategy formulation process. So you can divide and conquer, there's several leaders, like you assign different leaders to different people on the strategy working group and each of them sort talks to that leader. And there are a few questions that I would recommend asking, and it's basically, what does success feel like for the leader? What does failure look like? What is the measure of success? What are principles to keep in mind while going through this process? **Lenny Rachitsky** (00:23:51): And these are centered around the product that you're working on? **Chandra Janakiraman** (00:23:55): Exactly. **Lenny Rachitsky** (00:23:55): For Headspace, it'd be like, what do you think success looks like for Headspace or the specific feature of Headspace? [inaudible 00:24:03]. **Chandra Janakiraman** (00:24:02): Exactly. **Lenny Rachitsky** (00:24:03): Okay, cool. **Chandra Janakiraman** (00:24:04): That's right, yeah. And also I think ask them for their favorite or better ideas. It's actually what I've found through this process is a lot of leaders have these better ideas, they just feel shy to share it because they don't want their teams to think of them as micromanage-y. They want their teams to figure out the answer themselves, but then when you ask them, they actually have a pet idea always. (00:24:29): And so asking them just takes the mystery out of it. And it also gives them a creative avenue. So some people feel nervous about engaging senior leaders in these conversations in the sense that, hey, is it a waste of their time? What I've found is the exact opposite, senior leaders are, they welcome this because one, it's actually a more fun conversation for them than the other meetings that they have in their day because they're getting a little bit of their creative juices going, and they actually feel happy that somebody actually asked them what they're feeling and thinking about. And so it's actually very, very positive energy when you ask leaders just what they want. And it's also not a sign of weakness. It's actually a sign of strength and humility to ask your leaders what you want. And so keeping that fruit story in mind, I want to just say that this is a very, very positive thing, a very powerful thing. (00:25:26): The next area is competitive analysis. So if there is a product marketing person, they can do it for you. If there isn't, the PM should do it themselves. And basically the idea is you try to understand who are the comparables or the competitors in the space, and you sort of build a little bit of a head-to-head and sort a stack chart of where's everybody going and what are of the angles of investment for different people based on the explicit signals, which is what are they releasing? (00:25:59): You don't really know what their strategies are, but you can kind of tell when you look at the features they're putting out that, oh, they seem to be focusing on this particular area. And so that's sort of competitive analysis. And bigger companies, there's also another important input, which is adjacent roadmaps. Are the teams adjacent to you and what are they investing in? Because oftentimes that can have a rub-off effect on your team, and if you're not aligning with other key teams, it's going to be important. So adjacent roadmaps and a summary of that. (00:26:33): And last but not least, is what I call user observation. So I like the strategy working group to actually either interview a user or watch a video and report key learnings. And the idea is not to action those insights, it's really to build empathy. When you get somebody in the room with a user, it just changes their mind, it softens them a little bit. It gets them out of their own preconceived notions of what to build, what the strategy should be and... **Chandra Janakiraman** (00:27:00): ... their own preconceived notions of what to build, what the strategy should be, and it humanizes the whole process. That I think is the purpose, but you still give them the homework of writing down what they learned because it's a little bit of a forcing function. (00:27:16): The output of all of this is what I call the comprehensive preparation readout. It is a single master deck where you sort of have the behavioral insights meta analysis, you have the UXR insights meta analysis, you have a download of the leadership interviews, you have the competitive stack charts, you have the adjacent roadmaps, and you have a section on user observations. It's a lot of work, but to your point, it can be done in parallel with your day jobs. You can multitask, and that's why you take about four weeks to do that. That sort of concludes the preparation phase. You get the deck, and that rolls into the strategy sprint, which is the next phase. I want to pause and see if you have any questions. **Lenny Rachitsky** (00:28:06): Yeah, I have a million questions, but I'm going to keep myself contained. Just to quickly summarize. Basically you kick off, we're going to start developing strategy for this product, and you were going to touch on this, but it may help just to talk about this right now. I know you have big S Strategy, small S strategy. This process, what's an example of the level of product scale that this process is for? Because I know you have another approach for a larger scale of a product, basically for a company. What's the best way to think about small S strategy, which is what we're going through? **Chandra Janakiraman** (00:28:37): Yeah, I think it's a good question, Lenny. I would say that the process works well at sort of a growth stage company or in a vertical within sort of a larger company. I think it scales pretty well. The main difference between this small S and big S is the time horizon aspect and the aspirational component, which we'll get to. **Lenny Rachitsky** (00:29:02): Okay, so this is a process you can use for entire company strategy of not a large company, not a massively, and then also just a product within a company? **Chandra Janakiraman** (00:29:11): Yeah. **Lenny Rachitsky** (00:29:11): Okay, perfect. Okay. Hey, we're kicking off strategy for this thing. Let's say VR Chat 2.0. You have this kickoff meeting with your working group. You assign action items and there's six things you ask everyone to do. Gather all the behavioral insights, all the user research insights that you've had, leadership interviews, interview people, ask what they want and see what they're hoping for, what success looks like, competitive analysis, adjacent roadmaps across other teams and user observations, just like watch users, see what's happening. You assign each of these tasks to different people in this working group. You set a deadline. We have to present this in say, four weeks. People go work on it. You meet ongoing as it's coming together, and then the output is a deck that you share. Do you share this deck with just that working group, or who do you share this deck with and read it out to? **Chandra Janakiraman** (00:30:02): Yeah. The deck is an output of the first phase, and then it flows into the second phase, which is a strategy sprint. You don't share the deck with anybody yet. **Lenny Rachitsky** (00:30:10): Got it. This is our secret. **Chandra Janakiraman** (00:30:11): In the strategy sprint, it's like a key thing. Yeah. **Lenny Rachitsky** (00:30:13): Awesome. Okay. I love how very concrete and actionable this is with time boxes and action items and the exact output you're looking for. I love this. Okay, cool. Basically what you're trying to do here is gather all of the input that will inform the strategy. **Chandra Janakiraman** (00:30:27): That's correct. **Lenny Rachitsky** (00:30:28): It's giving yourself time to do this, because if you think about it, the output is determined by the quality of your input. I love, it feels like a core component of this method is spend time creating, gathering all the input, all the best input, actually spend time there. Don't just make it a half-assed last minute thing. Okay. Amazing. Okay, let's talk about step two, which is the strategy sprint. **Chandra Janakiraman** (00:30:52): Yeah, so the strategy sprint is the heart of the process. This is sort of where you make the decision. If you recall, the definition of strategy is it forces choice to deploy resources into a few areas for maximum impact. The core of strategy is really picking those areas and the areas you're not going invest in. That happens in the strategy sprint, so really it's the heart of the process. (00:31:22): Typically, it's like a three to five day process. The first day is the share out date. Everybody has done some great work. They go in, they share what they've collected, what they've sort of learned. It brings everybody in the working group to the same state of understanding, the same state of consciousness on the state of the union. That's a great process where what I encourage people to do is write down things that you are, as you're listening, write down things that you find are problems for our users, things that are coming in the way of our growth and things that are sort of suboptimal for the business. (00:32:05): People take a lot of notes during that time and the people who are presenting are sharing everything they've learned. That's really day one. It's just absorbing a ton of information and writing down a ton of notes so people can kind of understand where all the problems are. It's a very problems focused process, and that's an important point. I'll get back to it when we talk about big S, which is different. Once people have that common awareness, shared knowledge of all the problems, day two is literally the most important day in the entire 8 to 12 weeks because that's where you actually make the choice. The way to flow through it, it's actually really important to flow through it correctly. The first step is really generating a whole bunch of problems, because people have been taking notes the previous day. (00:32:59): You start the day with, \"Hey, let's collect everybody's thoughts on what the problems are that are holding us back.\" It's a free flowing session. Everybody throws out their observations on what's holding us back, and you just capture all of that in a Google Sheets, for example. Over even an hour, you start to see these patterns emerging of like, there's these clusters of problems that are really holding us back. The next step is you do a joint clustering of related problems and you create these potentially, typically in my experience, I've seen about 10 to 15 clusters form of very related problems. The beauty of it is each of those bigger cluster, you actually know what the sub problems are within that cluster because you sort of generated it very organically. (00:33:55): Then you have, let's say 10 to 15 clusters. What you then do is you, because remember, because it started as a problem generation exercise, each of the clusters also has a name that is a problem, and so the next step is to flip it into an opportunity framing. Let me give you a couple of examples. (00:34:16): Let's say there's a bunch of problems around people don't really know where to find different things in our product, and they don't really know where to go, where to find a certain feature or a certain experience. There's let's say a lot of problems in that area, so difficulty finding things becomes the cluster, the problem cluster and discovery becomes the opportunity sort of framing of it. It's sort of the more positive framing of it. (00:34:46): Another example could be that people get a lot of content that they don't like. They see a lot of stuff that they don't like, and so they disengage with the product. The opportunity framing of that would be relevance. It's basically stuff that really matters to me. Maybe if it's a social product, then maybe people are finding it difficult to find friends and they are lonely because of that. The opportunity framing would be social connection. (00:35:20): Flipping all of those problem clusters into positive framing and opportunity framing is the next step. Then you're in a great spot because now all you have to do is you have to down select from those 10 to 15 opportunity areas into ideally three, maybe five, but I would recommend three because it creates more clarity and focus. The way to do that is really sort of ranking them on, I would say four or five key dimensions or criteria, and the first is expected impact. (00:35:56): Let's say you actually tackle that area. What is the expected impact to whatever matters to you as a company, as a business, as a product? The second dimension is certainty of impact. Certainty of impact is basically how concrete is the evidence that this is a problem? Sometimes you have really hard data, sometimes you have more anecdotal evidence, and so the confidence really depends on how big the problem's sizing and frequency is. Expected impact, certainty of impact. The third one is also very important, which is clarity of levers. (00:36:34): Do you actually have an idea of how you would solve it? If you don't, it's going to be really difficult to move the needle on it because you should kind of know that, okay, I can imagine these solutions could actually move the needle. I can actually launch this sort of nudge system that can help people find things. I can recommend people. I can recommend friends so that people can form friends quicker on the platform. You should have a sense of how you would solve that particular space. Is there clarity on levers? That's the third dimension. (00:37:08): The fourth dimension is super important, which is are the levers unique and differentiated to that particular team or company? Which is that if another team or company could build it better than this particular team or company, then it's probably not that differentiated. It's probably going to be pretty generic once you launch it. It's a combination of sort of like, is there a lot of impact here? How confident are we of the problem? Do we have a sense of the solutions? And basically, are we the team or company that has the capabilities and the skills to uniquely build it where other teams cannot? (00:37:52): Once you have that, and sometimes what happens is you don't have too much data, and so it's okay to have qualitative scores on this like high, medium, low, T-shirt scores, whatever that is. The key is you're doing it together as a strategy working group, and you're debating the scores and you're reasoning why it should be higher versus lower. There's a ton of alignment and collision that's happening when you're doing that, which is very healthy for the eventual outcome. (00:38:22): Once you do that, basically you can do a simple sort of addition of the scores and a sort, and what you have is basically the top three and you have the remaining 7 or 12 that are basically not the focus. That's the core of the process, is getting those opportunity areas and getting to a shared sense of how do we prioritize them and why? **Lenny Rachitsky** (00:38:51): Okay, and this is all done in a week. I know there's more to it. There's a couple more items that help you move from what","guestOnly":"in some ways represents both sort of product design and user research. So you do get the voice of the user from that perspective. And typically the PM is driving the strategy working group and the process, but that working group is actually the team that's going to collaboratively create the strategy doc. (00:19:59): And so in the preparation phase, there's usually a kickoff meeting where the PM pulls the team together, talks about the purpose of the process, lays out the different phases, and gives everybody a feel for what's going to happen in the next 8 to 12 weeks. And basically then creates a list of very discrete action items and deliverables for each of the stakeholders in the working group. So specifically, there's an action item around aggregating all the behavioral insights that the team might have around the product. And usually this is a combination of previous analysis that the team has run on the data side and potentially also feature launches and how they have done. So all kind of analytical analysis. (00:20:50): The ask is really to create a meta analysis of all of the analysis. So the data person on the strategy working group has to scan the historical archives at the company and sort of synthesize and condense that into a very sort of digestible macro themes and learnings about users. So that's sort of one preparation phase item. (00:21:16): The second is UXR insight. So again, there's probably a lot of soft hard signals about users, not just based on research that's run by user researchers, but also potentially from the customer service team, social channels, and basically a meta analysis of all of that into one very actionable and synthesized deck on all the insights on users. That's usually led by the design person and with support from their research team. And that's sort of the second action item. (00:21:53): The third action item is leadership interviews. So I sort of have this fun story of the fruit with leadership strategy reviews, which I want to share. So imagine, this is sort of how sometimes strategy reviews go, which is you bring a fruit to the reviewer and say, \"Hey, here's a mango, what do you think?\" And the reviewer says, \"I actually don't like mangoes.\" And you're like, \"Oh,\" you're sort of sad. You take it back, you bring an apple and you show, \"Hey, what do you think of an apple?\" And then the leader says, \"I actually stopped eating apples last year.\" And so you're disappointed again. You go back, you bring a banana. \"I hated bananas since I was a kid.\" And so it's a bit of a silly caricature of reviews, but there's a bit of grain of truth there, which is, imagine how frustrating that is for both the reviewer and the person who's reviewing. (00:22:54): And so it could be made so much better if you just engage with your leaders before you actually build a strategy. It's amazing how few people actually do that. And so the fruit story tells you, hey, imagine if you just asked the reviewer, \"Do you even like fruits?\" How much better the experience would've been for both parties. And so leadership interviews are a very important part of a strategy formulation process. So you can divide and conquer, there's several leaders, like you assign different leaders to different people on the strategy working group and each of them sort talks to that leader. And there are a few questions that I would recommend asking, and it's basically, what does success feel like for the leader? What does failure look like? What is the measure of success? What are principles to keep in mind while going through this process? **Chandra Janakiraman** (00:23:55): Exactly. **Chandra Janakiraman** (00:24:02): Exactly. **Chandra Janakiraman** (00:24:04): That's right, yeah. And also I think ask them for their favorite or better ideas. It's actually what I've found through this process is a lot of leaders have these better ideas, they just feel shy to share it because they don't want their teams to think of them as micromanage-y. They want their teams to figure out the answer themselves, but then when you ask them, they actually have a pet idea always. (00:24:29): And so asking them just takes the mystery out of it. And it also gives them a creative avenue. So some people feel nervous about engaging senior leaders in these conversations in the sense that, hey, is it a waste of their time? What I've found is the exact opposite, senior leaders are, they welcome this because one, it's actually a more fun conversation for them than the other meetings that they have in their day because they're getting a little bit of their creative juices going, and they actually feel happy that somebody actually asked them what they're feeling and thinking about. And so it's actually very, very positive energy when you ask leaders just what they want. And it's also not a sign of weakness. It's actually a sign of strength and humility to ask your leaders what you want. And so keeping that fruit story in mind, I want to just say that this is a very, very positive thing, a very powerful thing. (00:25:26): The next area is competitive analysis. So if there is a product marketing person, they can do it for you. If there isn't, the PM should do it themselves. And basically the idea is you try to understand who are the comparables or the competitors in the space, and you sort of build a little bit of a head-to-head and sort a stack chart of where's everybody going and what are of the angles of investment for different people based on the explicit signals, which is what are they releasing? (00:25:59): You don't really know what their strategies are, but you can kind of tell when you look at the features they're putting out that, oh, they seem to be focusing on this particular area. And so that's sort of competitive analysis. And bigger companies, there's also another important input, which is adjacent roadmaps. Are the teams adjacent to you and what are they investing in? Because oftentimes that can have a rub-off effect on your team, and if you're not aligning with other key teams, it's going to be important. So adjacent roadmaps and a summary of that. (00:26:33): And last but not least, is what I call user observation. So I like the strategy working group to actually either interview a user or watch a video and report key learnings. And the idea is not to action those insights, it's really to build empathy. When you get somebody in the room with a user, it just changes their mind, it softens them a little bit. It gets them out of their own preconceived notions of what to build, what the strategy should be and... **Chandra Janakiraman** (00:27:00): ... their own preconceived notions of what to build, what the strategy should be, and it humanizes the whole process. That I think is the purpose, but you still give them the homework of writing down what they learned because it's a little bit of a forcing function. (00:27:16): The output of all of this is what I call the comprehensive preparation readout. It is a single master deck where you sort of have the behavioral insights meta analysis, you have the UXR insights meta analysis, you have a download of the leadership interviews, you have the competitive stack charts, you have the adjacent roadmaps, and you have a section on user observations. It's a lot of work, but to your point, it can be done in parallel with your day jobs. You can multitask, and that's why you take about four weeks to do that. That sort of concludes the preparation phase. You get the deck, and that rolls into the strategy sprint, which is the next phase. I want to pause and see if you have any questions. **Chandra Janakiraman** (00:28:37): Yeah, I think it's a good question, Lenny. I would say that the process works well at sort of a growth stage company or in a vertical within sort of a larger company. I think it scales pretty well. The main difference between this small S and big S is the time horizon aspect and the aspirational component, which we'll get to. **Chandra Janakiraman** (00:29:11): Yeah. **Chandra Janakiraman** (00:30:02): Yeah. The deck is an output of the first phase, and then it flows into the second phase, which is a strategy sprint. You don't share the deck with anybody yet. **Chandra Janakiraman** (00:30:11): In the strategy sprint, it's like a key thing. Yeah. **Chandra Janakiraman** (00:30:27): That's correct. **Chandra Janakiraman** (00:30:52): Yeah, so the strategy sprint is the heart of the process. This is sort of where you make the decision. If you recall, the definition of strategy is it forces choice to deploy resources into a few areas for maximum impact. The core of strategy is really picking those areas and the areas you're not going invest in. That happens in the strategy sprint, so really it's the heart of the process. (00:31:22): Typically, it's like a three to five day process. The first day is the share out date. Everybody has done some great work. They go in, they share what they've collected, what they've sort of learned. It brings everybody in the working group to the same state of understanding, the same state of consciousness on the state of the union. That's a great process where what I encourage people to do is write down things that you are, as you're listening, write down things that you find are problems for our users, things that are coming in the way of our growth and things that are sort of suboptimal for the business. (00:32:05): People take a lot of notes during that time and the people who are presenting are sharing everything they've learned. That's really day one. It's just absorbing a ton of information and writing down a ton of notes so people can kind of understand where all the problems are. It's a very problems focused process, and that's an important point. I'll get back to it when we talk about big S, which is different. Once people have that common awareness, shared knowledge of all the problems, day two is literally the most important day in the entire 8 to 12 weeks because that's where you actually make the choice. The way to flow through it, it's actually really important to flow through it correctly. The first step is really generating a whole bunch of problems, because people have been taking notes the previous day. (00:32:59): You start the day with, \"Hey, let's collect everybody's thoughts on what the problems are that are holding us back.\" It's a free flowing session. Everybody throws out their observations on what's holding us back, and you just capture all of that in a Google Sheets, for example. Over even an hour, you start to see these patterns emerging of like, there's these clusters of problems that are really holding us back. The next step is you do a joint clustering of related problems and you create these potentially, typically in my experience, I've seen about 10 to 15 clusters form of very related problems. The beauty of it is each of those bigger cluster, you actually know what the sub problems are within that cluster because you sort of generated it very organically. (00:33:55): Then you have, let's say 10 to 15 clusters. What you then do is you, because remember, because it started as a problem generation exercise, each of the clusters also has a name that is a problem, and so the next step is to flip it into an opportunity framing. Let me give you a couple of examples.","wordCount":3000}