{"personSlug":"ivan-zhao","personName":"Ivan Zhao","chunkIndex":0,"sourceTitle":"Notion’s lost years, its near collapse during Covid, staying small to move fast, the joy and suffering of building horizontal, more | Ivan Zhao (CEO and co-founder)","sourceType":"podcast","sourceDate":"2025-03-06","text":" **Lenny Rachitsky** (00:00:00): The way you described the early years of Notion, you described the first three to four years as the lost years. **Ivan Zhao** (00:00:05): We try many different versions. The first version, okay, everybody can make and create their software, so let's just build a developer tool that's so easy that more people can do that. We tried that a couple of years and learned that actually most people just don't care. Our realization is actually let's hide our vision, which is everybody can create their software in the form factor that people do care. So what kind of tool do people use every day? Productivity software. It took us two years to realize we need to build a productivity tool. We called it sugar-coated broccoli. People don't want to eat the broccoli but people like sugar, so it gave them the sugar then hide your broccoli inside of it. **Lenny Rachitsky** (00:00:40): What other elements do you think are key to you finding something that actually ended up working? **Ivan Zhao** (00:00:44): What is the building a product or business. You want user. You want revenue. That's the product business. And building for something you want the world to have is building for your value. You have some taste. You have some aesthetic. There are different energy. You need to create a balance. Too much of yourself. Then there's no users. Then you're just doing our project. And too much for business, you're building a commodity. **Lenny Rachitsky** (00:01:03): The way you think about Notion, it's almost like a philosophy of how to work and be versus just a productivity tool. And so I'm just curious how you think about the relationship between tools and human potential. **Ivan Zhao** (00:01:15): Tools are extensions of us. And once they extend us, once we shape them, once we bring them to world, they can come back to shape us. **Lenny Rachitsky** (00:01:28): Today, my guest is Ivan Zhao. Ivan is the co-founder and CEO of Notion. Ivan is a really unique and also a deeply philosophical founder who doesn't do a lot of podcasts, so I'm really excited to share a glimpse into how he built one of the most beloved and most popular products in the world. (00:01:45): We talk about the first three to four years of Notion that he describes as the lost years, how he was able to get into a great school in China by winning a programming contest, the joy and suffering of building a successful horizontal product, plus his approach to staying lean and craft and making trade-offs and also leadership. Also, a wild story about how Notion almost died during COVID because the one database that everything lived in almost ran out of space. (00:02:10): **Ivan Zhao** (00:04:47): Thank you for having me. **Lenny Rachitsky** (00:04:48): I know you don't do a lot of podcasts, and so I'm very honored that you're here. I want to start with the story of Ivan. Your background is quite unique for a founder of a $10 billion plus tech company, and I don't think a lot of people know it. For example, you grew up in a small town in China. And the way you got out of there, the way you got into tech is pretty interesting. Can you just walk us through that early years of Ivan and how you got out there? **Ivan Zhao** (00:05:16): Yeah. I think a small town in China, the definition, it's actually 4 million people. It is called Urumqi. It's in the northwest desert part of China. So I grew up there and then I moved into... My mom took me to Beijing, the capital of China. And that's actually how I got into programming, coding, because I'm from somewhere else and in order to go into good school in the capital, you need to win some kind of competition. And there's different paths. You can get at math or you can get at programming like Information Olympiad. I was really into computer games at the time so of course I picked the programming one so I can play computers all day long. And I win some competition and got me to a good school. So that's how I got into programming. (00:06:05): Later then, I moved to Canada. When I moved to Canada, got into college, did not study computer science since I already knew how to code, but a lot of video games. Did a lot of art actually, art and science. By the time I graduated college, I realized most of my friends are artists. They need to make their websites, get web portfolio made. And I'm the only nerd in my art friend circle so I made three or four websites and realized, \"Oh, actually people don't know how to create with the software media, computing media.\" So that got me into want to create a product like Notion today which it allow more people to create tools, create software for their daily work and life. **Lenny Rachitsky** (00:06:49): Okay. So going back to get into a great school and to leave the small town, not so small, you had to enter a programming contest. And you placed first or second or how well did you actually do in this one? **Ivan Zhao** (00:07:05): Second in Beijing. **Lenny Rachitsky** (00:07:07): In Beijing, okay. **Ivan Zhao** (00:07:08): Pretty big. Beijing is a big city. **Lenny Rachitsky** (00:07:11): Okay. Incredible. Another stat or a story I heard is that you learned English by watching SpongeBob SquarePants. Is that real? **Ivan Zhao** (00:07:18): Yeah, it's real. I moved to Canada pretty late, 16 years old, and what I learned is in China you can learn English but it's typically just grammar and doing exams. What you're missing is the context, the culture. So you have to watch SpongeBob or Simpsons to get a sense of humor essentially. You can understand jokes. Watching cartoons, it's probably the easiest way to do that. **Lenny Rachitsky** (00:07:45): That's amazing. And there's another seminal moment in your path. I don't know if it was this point or later, but the Douglas Engelbart paper ended up being a very meaningful moment for you. **Ivan Zhao** (00:07:57): So while I was in Canada in last year of school working on trying to building website from our friends and building a creative tool for them, and then you just look into the history of a creative tool for software, for computing. Eventually arrived at 1960 and '70s. So you realize the first generation of computing pioneers, which is around San Francisco, Stanford areas, South Bay, they actually had the best ideas. For them, people like Douglas Engelbart, Alan Kay, Ted Nelson, those first generation pioneers, for them computing, there shouldn't be a separation between builders and users. It's the same medium. Engelbart's original paper called Augmenting Human Intellect, when I read that paper, it's like holy shit. If you are making software, if you know how to code or design, this is the highest leverage thing you can do for other people. So giving them the ability to use computing to augment their problem-solving ability or their intellect, that just got me obsessed with this problem and I want to start a company like Notion. **Lenny Rachitsky** (00:09:05): It makes me think of Steve Jobs's famous line of how the computer is a bicycle for the mind. **Ivan Zhao** (00:09:10): You know what? Steve Jobs is actually at fault of this in some strange ways. So the story is... Actually, the fact. It's not a story. Xerox PARC has working on the first-generation personal computers called Xerox Alto. Alan Kay was one of the main persons behind it. Alto runs down the system called Smalltalk, which is there's no separation between users and users' app. There's no thing called application. Everything is malleable. You can change the tools. So when Steve Jobs, the famous story is when he went to Xerox PARC to in demo with Alto, he does not... It's the first time he see graphic user interface, one of the first time, and it's also they present them with this Alto system that everything could change. But he did not see the power of it. Even when people would demonstrate like, \"Hey,\" Steve Jobs say, \"I don't like this direction of scroll bar direction. When you scroll up and down, it shouldn't scroll the opposite reverse direction.\" Then people just instantly change the scroll bar direction for him. (00:10:16): That's the power of the original Smalltalk Alto system. He only saw the graphic user interface. He did not see the underlying object or the environment power. As the generation of Steve Jobs and Bill Gates made PC, personal computing, popular and they stuck with this an application framework rather than the Smalltalk object framework. Then that has all the apps we have today and has the SaaS route we have today. **Lenny Rachitsky** (00:10:43): That vision of how products should be sounds very familiar and we'll talk about that later of how you think about Notion, but let's assume to the beginning of Notion, when we were chatting earlier, the way you described the early years of Notion, you started Notion in 2013 and some over 10 years ago at this point, you described the first three to four years is the lost years of Notion. And I think this is actually a really big deal for founders to hear about because there's all these companies these days, you hear these stats, they had 100 million ARR in two years, in under two years now. And you don't hear a lot of stories of companies of your scale and success that took three to four years to find product market fit essentially. What went on during these lost years as you described them and just how did you stick with it? That's a long time to stick with something that isn't working. **Ivan Zhao** (00:11:32): Because the goal is always building a computing tool. It's like what product is this? It's really hard to shape the product. The vision is, the dream is there, but the product is very... There's so many paths. We'll try many different versions. The first version to take, okay, everybody can make and create their software. So let's just build a developer tool that's so easy that more people can do that. We tried that a couple of years and learned that actually most people just don't care. The majority of people, they wake up, they have report due, they need to get their job done, they don't care creating software to optimize whatever they're doing. They don't care. So we give to our friends, give to investors. It did not resonate with people. (00:12:22): But we really want to build that tool so we just keep going and our realization is actually, let's hide our vision, which is everybody can create their software, in the form factor that people do care. So what kind of tool do people use every day? Productivity software. So that's why it came to Notion today. If you use Notion, Notion are more understood as the productivity suite, but our intent, and if you use Notion, more you discover intent, which is that it has a no-code developer power into it and you can create almost any kind of productivity software using Notion itself. That took us two plus year to realize. So actually the world is not like you. The world are not developer, designer mind. That the world is they only care what's in front of them and they're so noisy. **Lenny Rachitsky** (00:13:16): There's a quote that this makes me think about where you said, \"The first version of Notion was more about what I wanted than what people wanted.\" **Ivan Zhao** (00:13:23): It's very much so because sense of maturation is you don't see the world just from your perspective but from outside your perspective. At tech, we were young. Took us multiple years. It hit your head straight into the wall to realize that. People just don't care. **Lenny Rachitsky** (00:13:40): I love the way you phrased that, that you have to hide your vision behind something that people understand and know how to use and... **Ivan Zhao** (00:13:47): We call it sugar-coated broccoli. People don't want to eat the broccoli but people like sugar, so give them the sugar then hide the broccoli inside of it. **Lenny Rachitsky** (00:13:55): Wow. The other thing I've heard is that you threw away your code every time, so you rebuilt it many times. You threw away the code each time. **Ivan Zhao** (00:14:03): That's true. Actually, it took us four year to get somewhere. First two year is that you build too much like developer product. Nobody cares. It took us two year to realize we need to build a productivity tool. Then it took another year to realize to build this out, but in the middle of that I realized we built on the wrong technical foundation. So eight, 10 years ago, there's computing before. Right now, all the web app runs on React. Before React wins, there's a competing technology called Web Component from Google. And it makes sense. Web Component feels like a Lego-like, the building block-like, and we're betting on that technology. And then we realize because it's so new, it's just so unstable. It don't know where the bug come from. It's from your source code or from the underlying libraries? Then we have to restart the company, rebuild the whole thing. Otherwise, we're going to run out of time. So we set a code base. We set a company so we can build on our own more orthodox technology foundation. **Lenny Rachitsky** (00:15:10): How did you actually stay solvent all this time? A lot of people want to keep working at an idea. Oftentimes they need to pay the bills. How practically were you able to keep working for three to four years? I know there's a story of your mom loaning you some money during that time. **Ivan Zhao** (00:15:25): Well, Chinese mom always can help, and I'm a single child. Yeah, actually my mom helped me kickstart the company because I'm Canadian. In order to move to US, you need to register a company. So my mom helped me with the initial and raised the money. I returned the money to her. Then we run out of the money so, \"Hey mom, can I borrow that just to bridge us?\" Which she did. I'm really grateful for that. How we bridged? How do you last here so long? Because the thing you want to create does not exist, which what is called Notions. It's a Lego for software. It doesn't quite exist. There's a Lego for Lego. You can see that in furniture exist, but Lego for software at the usable mass market adoption level doesn't quite exist. And you just want that thing to exist. And I grew up with Legos. It's the only toy I ever wanted, and I want the same feeling of creativity and playfulness to the toy that people can use every day. And my co-founder, Simon, feels the same way. Lego is the only thing he wanted for every Christmas. **Lenny Rachitsky** (00:16:36): Have you guys seen Magna-Tiles though? I have a one-and-a-half-year-old and Magna-Tiles are quite delightful. I think it's like a pre-Lego. The children can play them. **Ivan Zhao** (00:16:45): Magna-Tile? **Lenny Rachitsky** (00:16:46): Yeah. It's like they're little magnetic plastic planes and then you can build much bigger things really quickly. It's more for babies, but I'm having a blast. **Ivan Zhao** (00:17:01): Oh, I see it. It's like... Uh-huh. **Lenny Rachitsky** (00:17:02): It's a different version of Legos. I like that you're in real-time looking it up. You're like, \"Okay, our new vision Magna-Tiles for software.\" **Ivan Zhao** (00:17:08): Now, most people know, \"Oh, Magna-Tile.\" Idea is the same. Modular, right? **Lenny Rachitsky** (00:17:13): Yeah, creativity. Okay, back to your story. So there's also a moment where you moved to Japan. Just what was that about? Is that just escape and disconnect? **Ivan Zhao** (00:17:20): Yeah, that was during one of the rebuild phases. During the... We know what the product should look like. It should be a productivity software with a Lego power hiding inside of it. We build on the wrong technical foundation. And if we continue to build on the wrong ones, we're going to run out of money. Company won't exist. So we decided to lay off everybody. At that time, the Notion was five people. The layout I brought back to me and Simon, two people. And morale obviously there was really low. You have to say goodbye to your teammates. And so we have the idea, \"Let's just go somewhere that we've never been to change the scenery a little bit.\" And Japan is always top on our list. (00:18:00): So the funny thing is if we... And we subleased our apartment and office. We're actually making money living in Japan and then San Francisco. So we did that for a while. We actually travel around the world for a while just to change it up, me and Sam just coding every day and design every day. That's some of the happiest moments. Birthday every day. **Lenny Rachitsky** (00:18:27): I saw a stat you're coding 18 hours a day. Here's the quote I heard, :We just code, code, code. Then hey, let's go for food. Then we go eat, go back to work, and do it again.\" **Ivan Zhao** (00:18:35): Because me and him working so well now. Even back then, it's like you know what each other other people are thinking and you can just cross through the problem space really quickly. The technical product space, design space, and","guestOnly":"**Ivan Zhao** (00:00:05): We try many different versions. The first version, okay, everybody can make and create their software, so let's just build a developer tool that's so easy that more people can do that. We tried that a couple of years and learned that actually most people just don't care. Our realization is actually let's hide our vision, which is everybody can create their software in the form factor that people do care. So what kind of tool do people use every day? Productivity software. It took us two years to realize we need to build a productivity tool. We called it sugar-coated broccoli. People don't want to eat the broccoli but people like sugar, so it gave them the sugar then hide your broccoli inside of it. **Ivan Zhao** (00:00:44): What is the building a product or business. You want user. You want revenue. That's the product business. And building for something you want the world to have is building for your value. You have some taste. You have some aesthetic. There are different energy. You need to create a balance. Too much of yourself. Then there's no users. Then you're just doing our project. And too much for business, you're building a commodity. **Ivan Zhao** (00:01:15): Tools are extensions of us. And once they extend us, once we shape them, once we bring them to world, they can come back to shape us. **Ivan Zhao** (00:04:47): Thank you for having me. **Ivan Zhao** (00:05:16): Yeah. I think a small town in China, the definition, it's actually 4 million people. It is called Urumqi. It's in the northwest desert part of China. So I grew up there and then I moved into... My mom took me to Beijing, the capital of China. And that's actually how I got into programming, coding, because I'm from somewhere else and in order to go into good school in the capital, you need to win some kind of competition. And there's different paths. You can get at math or you can get at programming like Information Olympiad. I was really into computer games at the time so of course I picked the programming one so I can play computers all day long. And I win some competition and got me to a good school. So that's how I got into programming. (00:06:05): Later then, I moved to Canada. When I moved to Canada, got into college, did not study computer science since I already knew how to code, but a lot of video games. Did a lot of art actually, art and science. By the time I graduated college, I realized most of my friends are artists. They need to make their websites, get web portfolio made. And I'm the only nerd in my art friend circle so I made three or four websites and realized, \"Oh, actually people don't know how to create with the software media, computing media.\" So that got me into want to create a product like Notion today which it allow more people to create tools, create software for their daily work and life. **Ivan Zhao** (00:07:05): Second in Beijing. **Ivan Zhao** (00:07:08): Pretty big. Beijing is a big city. **Ivan Zhao** (00:07:18): Yeah, it's real. I moved to Canada pretty late, 16 years old, and what I learned is in China you can learn English but it's typically just grammar and doing exams. What you're missing is the context, the culture. So you have to watch SpongeBob or Simpsons to get a sense of humor essentially. You can understand jokes. Watching cartoons, it's probably the easiest way to do that. **Ivan Zhao** (00:07:57): So while I was in Canada in last year of school working on trying to building website from our friends and building a creative tool for them, and then you just look into the history of a creative tool for software, for computing. Eventually arrived at 1960 and '70s. So you realize the first generation of computing pioneers, which is around San Francisco, Stanford areas, South Bay, they actually had the best ideas. For them, people like Douglas Engelbart, Alan Kay, Ted Nelson, those first generation pioneers, for them computing, there shouldn't be a separation between builders and users. It's the same medium. Engelbart's original paper called Augmenting Human Intellect, when I read that paper, it's like holy shit. If you are making software, if you know how to code or design, this is the highest leverage thing you can do for other people. So giving them the ability to use computing to augment their problem-solving ability or their intellect, that just got me obsessed with this problem and I want to start a company like Notion. **Ivan Zhao** (00:09:10): You know what? Steve Jobs is actually at fault of this in some strange ways. So the story is... Actually, the fact. It's not a story. Xerox PARC has working on the first-generation personal computers called Xerox Alto. Alan Kay was one of the main persons behind it. Alto runs down the system called Smalltalk, which is there's no separation between users and users' app. There's no thing called application. Everything is malleable. You can change the tools. So when Steve Jobs, the famous story is when he went to Xerox PARC to in demo with Alto, he does not... It's the first time he see graphic user interface, one of the first time, and it's also they present them with this Alto system that everything could change. But he did not see the power of it. Even when people would demonstrate like, \"Hey,\" Steve Jobs say, \"I don't like this direction of scroll bar direction. When you scroll up and down, it shouldn't scroll the opposite reverse direction.\" Then people just instantly change the scroll bar direction for him. (00:10:16): That's the power of the original Smalltalk Alto system. He only saw the graphic user interface. He did not see the underlying object or the environment power. As the generation of Steve Jobs and Bill Gates made PC, personal computing, popular and they stuck with this an application framework rather than the Smalltalk object framework. Then that has all the apps we have today and has the SaaS route we have today. **Ivan Zhao** (00:11:32): Because the goal is always building a computing tool. It's like what product is this? It's really hard to shape the product. The vision is, the dream is there, but the product is very... There's so many paths. We'll try many different versions. The first version to take, okay, everybody can make and create their software. So let's just build a developer tool that's so easy that more people can do that. We tried that a couple of years and learned that actually most people just don't care. The majority of people, they wake up, they have report due, they need to get their job done, they don't care creating software to optimize whatever they're doing. They don't care. So we give to our friends, give to investors. It did not resonate with people. (00:12:22): But we really want to build that tool so we just keep going and our realization is actually, let's hide our vision, which is everybody can create their software, in the form factor that people do care. So what kind of tool do people use every day? Productivity software. So that's why it came to Notion today. If you use Notion, Notion are more understood as the productivity suite, but our intent, and if you use Notion, more you discover intent, which is that it has a no-code developer power into it and you can create almost any kind of productivity software using Notion itself. That took us two plus year to realize. So actually the world is not like you. The world are not developer, designer mind. That the world is they only care what's in front of them and they're so noisy. **Ivan Zhao** (00:13:23): It's very much so because sense of maturation is you don't see the world just from your perspective but from outside your perspective. At tech, we were young. Took us multiple years. It hit your head straight into the wall to realize that. People just don't care. **Ivan Zhao** (00:13:47): We call it sugar-coated broccoli. People don't want to eat the broccoli but people like sugar, so give them the sugar then hide the broccoli inside of it. **Ivan Zhao** (00:14:03): That's true. Actually, it took us four year to get somewhere. First two year is that you build too much like developer product. Nobody cares. It took us two year to realize we need to build a productivity tool. Then it took another year to realize to build this out, but in the middle of that I realized we built on the wrong technical foundation. So eight, 10 years ago, there's computing before. Right now, all the web app runs on React. Before React wins, there's a competing technology called Web Component from Google. And it makes sense. Web Component feels like a Lego-like, the building block-like, and we're betting on that technology. And then we realize because it's so new, it's just so unstable. It don't know where the bug come from. It's from your source code or from the underlying libraries? Then we have to restart the company, rebuild the whole thing. Otherwise, we're going to run out of time. So we set a code base. We set a company so we can build on our own more orthodox technology foundation. **Ivan Zhao** (00:15:25): Well, Chinese mom always can help, and I'm a single child. Yeah, actually my mom helped me kickstart the company because I'm Canadian. In order to move to US, you need to register a company. So my mom helped me with the initial and raised the money. I returned the money to her. Then we run out of the money so, \"Hey mom, can I borrow that just to bridge us?\" Which she did. I'm really grateful for that. How we bridged? How do you last here so long? Because the thing you want to create does not exist, which what is called Notions. It's a Lego for software. It doesn't quite exist. There's a Lego for Lego. You can see that in furniture exist, but Lego for software at the usable mass market adoption level doesn't quite exist. And you just want that thing to exist. And I grew up with Legos. It's the only toy I ever wanted, and I want the same feeling of creativity and playfulness to the toy that people can use every day. And my co-founder, Simon, feels the same way. Lego is the only thing he wanted for every Christmas. **Ivan Zhao** (00:16:45): Magna-Tile? **Ivan Zhao** (00:17:01): Oh, I see it. It's like... Uh-huh. **Ivan Zhao** (00:17:08): Now, most people know, \"Oh, Magna-Tile.\" Idea is the same. Modular, right? **Ivan Zhao** (00:17:20): Yeah, that was during one of the rebuild phases. During the... We know what the product should look like. It should be a productivity software with a Lego power hiding inside of it. We build on the wrong technical foundation. And if we continue to build on the wrong ones, we're going to run out of money. Company won't exist. So we decided to lay off everybody. At that time, the Notion was five people. The layout I brought back to me and Simon, two people. And morale obviously there was really low. You have to say goodbye to your teammates. And so we have the idea, \"Let's just go somewhere that we've never been to change the scenery a little bit.\" And Japan is always top on our list. (00:18:00): So the funny thing is if we... And we subleased our apartment and office. We're actually making money living in Japan and then San Francisco. So we did that for a while. We actually travel around the world for a while just to change it up, me and Sam just coding every day and design every day. That's some of the happiest moments. Birthday every day. **Ivan Zhao** (00:18:35): Because me and him working so well now. Even back then, it's like you know what each other other","wordCount":3000}