{"personSlug":"wes-kao","personName":"Wes Kao","chunkIndex":0,"sourceTitle":"Become a better communicator: Specific frameworks to improve your clarity, influence, and impact | Wes Kao (coach, entrepreneur, advisor)","sourceType":"podcast","sourceDate":"2025-04-06","text":" Wes Kao (00:00): I think that most people assume that their boss has to manage them and they feel a little bit resentful that, why should I manage my boss? They're getting paid more. They are my manager. They have more responsibility. Wes Kao (00:14): And you can continue to think that way and your career might be fine, but if you embrace that if you manage your boss, they're going to appreciate you much more, you're going to get more opportunities, you're going to have more trust with them, there's all these great things that happen when you decide to manage up. Lenny (00:36): Wes Kao is the co-founder of Maven, a cohort-based learning platform that I used to create my own course on product management. But even more interestingly, she's helped folks like Seth Godin start his altMBA course, which is legendary. She's also helped people like David Perell, Tiago Forte, Scott Galloway, and even Morning Brew build their cohort-based courses. She's one of the smartest people I have ever met on the art of teaching and I've learned a ton from her. Lenny (01:01): And in our chat, we cover a concept I love called the super specific who. We talk about the state change method and how using this idea, you'll run better meetings. We look at a bunch of advice for why you should spend time managing up and how to manage up effectively. We talk about a bunch of ways to write better, tips for saying no, and a bunch of other really interesting topics. I always have such a good time chatting with Wes, and I hope that you learn as much from this chat as I did. And with that, I bring you Wes Kao. Lenny (01:36): This episode is brought to you by Modern Treasury. Modern Treasury is a next generation operating system for moving and tracking money. They're modernizing the developer tools and financial processes for companies managing complex payment flows. Think digital wallets, fiat crypto on-ramps, ride sharing marketplaces, instant lending and more. They work with high growth companies like Gusto, Hype, ClassPass and Marqeta. Lenny (02:02): Modern Treasury's robust APIs allow engineering to build payment flows right into your product while finance can monitor and approve everything through a sleek and modern web dashboard, enabling realtime payments, automatic reconciliation, continuous accounting and compliance solutions. Modern Treasury's platform is used to reconcile over $3 billion per month. Lenny (02:23): They're one of the hottest young FinTech startups on the market today, having raised funding from top firms like Benchmark, Altimeter, SVB Capital, Salesforce Ventures, and Y Combinator. Check them out at moderntreasury.com. Lenny (02:37): This episode is brought to you by Berbix. Whether you're in the business of crypto or renting out vehicles or selling age restricted goods, it's important to have the confidence that who you're selling to is who they say they are. With Berbix, businesses can quickly and easily verify someone's identity through their government issued ID and real-time selfie. Lenny (02:58): Unlike other identity verification, software solutions, Berbix takes only seconds to verify an identity helping you maximize conversion and mitigate fraud. With Berbix, you can grow revenue by instantly verifying a customer's drivers license, passport, or ID card. You can also deter fraud by customizing which transactions you want to accept or reject based on triggers like duplicate IDs, expiration dates, or user session location. Lenny (03:24): Get started quickly by setting up Berbix with no code, low code, or complete integration in as little as one afternoon. Visit berbix.com/start to get started. That's B-E-R-B-I-X.com/start. Lenny (03:42): Wes, I have learned so much from you over the years in so many different ways, while building my course, through your writing, through your tweets. And generally you're just a super fascinating human that I love this excuse to get to learn more about you and for listeners to learn more about you. And so with that, Wes, welcome to the podcast. Wes Kao (04:01): Hey, Lenny. Great to be here. Lenny (04:03): It's my pleasure. So just to set a little context about the Wes that we know today, your career path has been pretty untraditional for many of the guests that we've had on this podcast. And so I'd love to just hear a brief, high level overview of your career and understand what made Wes the Wes that she is today. Wes Kao (04:23): I started my career in corporate retail at the Gap headquarters in San Francisco. So I did a rotational training program, rotating between Old Navy, Banana Republic, Gap, and it was a great foundation in business fundamentals. Wes Kao (04:39): A lot of people talk about, should I out of school go to a bigger company, or should I go to a startup? So I went to a bigger company and gradually have gone to smaller companies since then until finally starting my own in the past 15 years. Wes Kao (04:55): So I think that getting to see inside what a company that's been around for 40 plus years was like was really, really fantastic training and set me up for success for jumping into tech and other roles since then. Wes Kao (05:11): After Gap, I went to a beauty company that was acquired by Shiseido and then was at an ad tech company that was acquired by Snap. And then moved cross country from SF to New York to work with bestselling author, Seth Godin. Wes Kao (05:26): And that just changed my trajectory completely. It was just such a transformative experience getting to learn and work directly with for three years, one of the best marketing minds and just most creative minds, I think on the planet right now. Wes Kao (05:42): And together we co-founded the altMBA, which I grew from just an idea between me and Seth, to thousands of students, 45 countries, 500 cities, grew our team from just us two to 60 plus people all over the world. So it was just an amazing, amazing experience. Wes Kao (05:59): And then after that, I consulted for a couple of years working directly with other course creators who wanted to create their mini versions of the altMBA, and from doing that, really proved out the idea that the format of cohort-based courses was something that was really special, that other experts in other industries, other functions could really leverage. Wes Kao (06:19): And then that led to starting Maven because when I was consulting and when I was doing altMBA, during those six, seven years, I realized how janky the tech stack was that everyone was using. And I was shocked that no one had tackled this problem of all of us course creators needing to toggle between half a dozen different tools just to make a live plus async course be able to work. Wes Kao (06:44): And so when my co-founder Gagan Biyani and I got together, we were brainstorming what's the future of education and catching up. And we were just shocked that, hey, why hasn't anyone tackled this yet? We should do this because we both really believe that cohort-based courses are the future that [inaudible 00:07:02] want to teach these courses, but it's just too hard from a technical perspective now, but it doesn't have to be that way. Lenny (07:07): Awesome. I definitely want to chat a bit about Seth Godin. I've been such a huge fan of his for, I don't know, a decade. I used to subscribe to his newsletter and I don't anymore, because it's an email every day and it's overwhelming, even though he pointed out in one of his newsletters, okay, just ignore it. Why would you be sad that I have so much content? But yeah, anyway I unsubscribed recently, but I'm such a fan. And so I'm so curious, one, how did you connect with him and how did that even happen? And then two, what is he like to work with? Wes Kao (07:37): Both very, very juicy questions. So the way that we connected was Seth had put out a blog post saying that he was looking for a special projects lead to help him figure out what to do next. So this was in 2014 when he had just sold off his last company Squidoo that he had been working on for I think, eight years or so before that. Wes Kao (07:57): So he was ready for something new, at a crossroads, wanted some fresh inspiration, and I saw this blog post on a whim. And at that time I was at that ad tech company in San Francisco and I thought there are probably thousands of people who are going to be applying to this, so I don't want to get my hopes up. I did want to move to New York. I feel like everyone in SF and California at some time wants to move to New York. And so I thought, all right, I'm going to toss my hat in the ring and not overthink it. Wes Kao (08:25): And so the application required a video, so there was a written application and then there was a video. So Seth said, \"Take three minutes to talk about what you want to build, what you want to contribute, and what you want to learn,\" something along those lines. Wes Kao (08:39): And I did my video in one take. Normally I would've done multiple takes for sure, but here I just thought there's a very little chance I'm going to get this. And a couple days later to my surprise, I get an email from Seth Godin. He's in my inbox and I'm just jumping up and down in my living room because he's asked, \"Hey, loved your video. Let's hop on a call for an interview.\" And of course I write a very calm professional response and we did a couple rounds of interviews and I get the role. Wes Kao (09:06): So I pack my life into six suitcases, get an apartment sight unseen in this little town right outside of New York City, where Seth's office is, it's called Hastings-on-Hudson. And what initially started off as a six month role eventually led to over three years working together and starting the altMBA together. Wes Kao (09:24): So that's how we got connected, very serendipitous. But my lesson there is don't take yourself out of the running before you get rejected. Don't reject yourself, basically. I think a lot of us have high standards and high expectations of ourselves and it's almost like, oh, if I can't do the best application, then I just shouldn't apply. If I don't have time to take five takes of this video, it won't be good enough, and so I just shouldn't do it. So for me, that was a great lesson in putting your best foot forward, but putting your foot forward. Lenny (09:55): I love that. Wes Kao (09:57): So that was how we got connected. And then in terms of what it was like working with him, I think the Seth that people know externally can sometimes be different from the behind-the-scenes Seth. And that I think that's true for all of us, by the way. And so I think externally, he can sometimes be a little bit of a vague Buddha, if you will. He gives great inspiring advice. His insights, I think are amazing. Wes Kao (10:22): If you look at his blog, some people try to copy Seth's blog by writing short daily posts, but that is not the reason why Seth's blog is so good. That is incidental, that they are short and daily. The reason why it works is because they are so insight rich. Wes Kao (10:39): And in person, he is even smarter and even sharper than he is in writing and online, which is so amazing. I'm just shocked by that because I feel like most people are the opposite. It's like you have time to curate what goes on your Twitter, your website. You have time to manicure this, what you want people to think of you, but when you are live, you're there with the person, you're talking like normal people and you can really get a sense of how sharp or insightful or genuine someone is. And I think he's even more genuine, even sharper, even funnier in person. Wes Kao (11:12): So that was kind of high level. I think the other thing is that internally we had really high standards for what we would ship, which is a little bit different, I think, than what you might think if you were a Seth reader. Because before I would read him and just do it, essentially, ship, put yourself out there, don't overthink it. Wes Kao (11:34): And you might think that, that means that there's a trade-off with quality, but the thing that I found so surprising about working together was that we often produced work almost always that was high quality, fast, and what's that third thing of that triangle? Cheap, or not cheap, but affordable or economical. Usually it's like, oh, you only get two of these or there's the trade-off between quality and speed, but we worked fast and we produced really great work. Wes Kao (12:06): And so I think for me, it really raised the bar on everything for me and on strategies, on tactics, on expectations, on quality, speed. I think the speed that we shipped ... Before I was at a Sequoia-backed ad tech startup and I thought, oh, I know what shipping fast is, I was at a startup. Wes Kao (12:26): And the speed that we shipped at Seth HQ was just beyond. It just blew away what I think normal people think of as fast, but it was also still so good. And so I think that rigor and that refusal to accept anything but excellence was just so awesome. And it really spoke to me because I care a lot about craft. I think more people should care about craft and I'm also kind of an obsessed person. I have an obsessive personality and I just loved how Seth was similarly obsessed. And so yeah, learned so much from him that I've taken with me obviously in building Maven now and everything that I do. Lenny (13:12): Wow. I've 10 more questions I'd love to ask about Seth Godin, but I should probably try to get him on the podcast. What a coup that would be. I have a sad story actually. I just remembered while you were talking, I saw him mentioned once that he replies to every email he gets. And so I emailed him because- Wes Kao (13:30): Just to check. Lenny (13:31): ... I had such a crush. Yeah, just to test. And he replied and he's like, \"Why would I say this if I wasn't doing this? What benefit would that be for me?\" I was like, \"Oh shit, I pissed him off. Wes Kao (13:40): So funny. Lenny (13:40): He hates me. Wes Kao (13:43): It's hilarious. Lenny (13:44): Oh man. Okay. Amazing. One last quick question. You also worked with Scott Galloway, who's a very polarizing figure on Twitter at least, and you helped him create his courses. Maybe just one quick question on him, what's he like and why do people dislike him so much on Twitter? Wes Kao (14:00): Yeah, I don't know about people disliking him. He definitely has spiky points of view, which I think are amazing. Yeah. So Section4, Scott Galloway's company was one of the first clients that I worked with after leaving altMBA, and I didn't work too closely with Scott. I worked really closely with his CEO, Greg Shove and their exec team to design the sprint that's now their go-to course format. But yeah, I didn't work too closely with him directly. Lenny (14:27): Okay, cool. We won't get too deep there. Okay, so what I want to do with most of the time that we have together is to go into five big ideas. You could call it the five big ideas from Wes Kao, concepts that you've shared in other places that you've touched on your writing and tweeting and things like that have struck and have stuck with me and I suspect many other people, and just go deeper on these ideas. Does that sound good? Wes Kao (14:49): Sounds great. Lenny (14:51): Awesome. So the first idea I want to chat about is something you call the super specific how. And you wrote a post about this and it really clarified a lot of my thinking on writing and the newsletter and the podcast. And I find myself sharing this post and concept with other writers who are struggling a bit with their content. And so can you just explain this idea of the super specific how, and generally just how it can make folks better writers and thinkers? Wes Kao (15:18): Yeah. The idea of the super specific how is that most writers, most course instructors spend too much time on the what and the why and not enough time on how. So if you think about people who are reading your writing, most of them probably already agree with the general premise of what you're saying. Wes Kao (15:44): Unless what you're saying is truly controversial, a ground-breaker, or new to your audience, you don't need to spend too much time elaborating on the concept itself and why it matters. People really want to know how do I do this? How do I apply this to my own life? How do I think about the nuances when I'm applying this? What are examples that I can look at that help me better internalize how this","guestOnly":" Wes Kao (00:00): I think that most people assume that their boss has to manage them and they feel a little bit resentful that, why should I manage my boss? They're getting paid more. They are my manager. They have more responsibility. Wes Kao (00:14): And you can continue to think that way and your career might be fine, but if you embrace that if you manage your boss, they're going to appreciate you much more, you're going to get more opportunities, you're going to have more trust with them, there's all these great things that happen when you decide to manage up. Lenny (00:36): Wes Kao is the co-founder of Maven, a cohort-based learning platform that I used to create my own course on product management. But even more interestingly, she's helped folks like Seth Godin start his altMBA course, which is legendary. She's also helped people like David Perell, Tiago Forte, Scott Galloway, and even Morning Brew build their cohort-based courses. She's one of the smartest people I have ever met on the art of teaching and I've learned a ton from her. Lenny (01:01): And in our chat, we cover a concept I love called the super specific who. We talk about the state change method and how using this idea, you'll run better meetings. We look at a bunch of advice for why you should spend time managing up and how to manage up effectively. We talk about a bunch of ways to write better, tips for saying no, and a bunch of other really interesting topics. I always have such a good time chatting with Wes, and I hope that you learn as much from this chat as I did. And with that, I bring you Wes Kao. Lenny (01:36): This episode is brought to you by Modern Treasury. Modern Treasury is a next generation operating system for moving and tracking money. They're modernizing the developer tools and financial processes for companies managing complex payment flows. Think digital wallets, fiat crypto on-ramps, ride sharing marketplaces, instant lending and more. They work with high growth companies like Gusto, Hype, ClassPass and Marqeta. Lenny (02:02): Modern Treasury's robust APIs allow engineering to build payment flows right into your product while finance can monitor and approve everything through a sleek and modern web dashboard, enabling realtime payments, automatic reconciliation, continuous accounting and compliance solutions. Modern Treasury's platform is used to reconcile over $3 billion per month. Lenny (02:23): They're one of the hottest young FinTech startups on the market today, having raised funding from top firms like Benchmark, Altimeter, SVB Capital, Salesforce Ventures, and Y Combinator. Check them out at moderntreasury.com. Lenny (02:37): This episode is brought to you by Berbix. Whether you're in the business of crypto or renting out vehicles or selling age restricted goods, it's important to have the confidence that who you're selling to is who they say they are. With Berbix, businesses can quickly and easily verify someone's identity through their government issued ID and real-time selfie. Lenny (02:58): Unlike other identity verification, software solutions, Berbix takes only seconds to verify an identity helping you maximize conversion and mitigate fraud. With Berbix, you can grow revenue by instantly verifying a customer's drivers license, passport, or ID card. You can also deter fraud by customizing which transactions you want to accept or reject based on triggers like duplicate IDs, expiration dates, or user session location. Lenny (03:24): Get started quickly by setting up Berbix with no code, low code, or complete integration in as little as one afternoon. Visit berbix.com/start to get started. That's B-E-R-B-I-X.com/start. Lenny (03:42): Wes, I have learned so much from you over the years in so many different ways, while building my course, through your writing, through your tweets. And generally you're just a super fascinating human that I love this excuse to get to learn more about you and for listeners to learn more about you. And so with that, Wes, welcome to the podcast. Wes Kao (04:01): Hey, Lenny. Great to be here. Lenny (04:03): It's my pleasure. So just to set a little context about the Wes that we know today, your career path has been pretty untraditional for many of the guests that we've had on this podcast. And so I'd love to just hear a brief, high level overview of your career and understand what made Wes the Wes that she is today. Wes Kao (04:23): I started my career in corporate retail at the Gap headquarters in San Francisco. So I did a rotational training program, rotating between Old Navy, Banana Republic, Gap, and it was a great foundation in business fundamentals. Wes Kao (04:39): A lot of people talk about, should I out of school go to a bigger company, or should I go to a startup? So I went to a bigger company and gradually have gone to smaller companies since then until finally starting my own in the past 15 years. Wes Kao (04:55): So I think that getting to see inside what a company that's been around for 40 plus years was like was really, really fantastic training and set me up for success for jumping into tech and other roles since then. Wes Kao (05:11): After Gap, I went to a beauty company that was acquired by Shiseido and then was at an ad tech company that was acquired by Snap. And then moved cross country from SF to New York to work with bestselling author, Seth Godin. Wes Kao (05:26): And that just changed my trajectory completely. It was just such a transformative experience getting to learn and work directly with for three years, one of the best marketing minds and just most creative minds, I think on the planet right now. Wes Kao (05:42): And together we co-founded the altMBA, which I grew from just an idea between me and Seth, to thousands of students, 45 countries, 500 cities, grew our team from just us two to 60 plus people all over the world. So it was just an amazing, amazing experience. Wes Kao (05:59): And then after that, I consulted for a couple of years working directly with other course creators who wanted to create their mini versions of the altMBA, and from doing that, really proved out the idea that the format of cohort-based courses was something that was really special, that other experts in other industries, other functions could really leverage. Wes Kao (06:19): And then that led to starting Maven because when I was consulting and when I was doing altMBA, during those six, seven years, I realized how janky the tech stack was that everyone was using. And I was shocked that no one had tackled this problem of all of us course creators needing to toggle between half a dozen different tools just to make a live plus async course be able to work. Wes Kao (06:44): And so when my co-founder Gagan Biyani and I got together, we were brainstorming what's the future of education and catching up. And we were just shocked that, hey, why hasn't anyone tackled this yet? We should do this because we both really believe that cohort-based courses are the future that [inaudible 00:07:02] want to teach these courses, but it's just too hard from a technical perspective now, but it doesn't have to be that way. Lenny (07:07): Awesome. I definitely want to chat a bit about Seth Godin. I've been such a huge fan of his for, I don't know, a decade. I used to subscribe to his newsletter and I don't anymore, because it's an email every day and it's overwhelming, even though he pointed out in one of his newsletters, okay, just ignore it. Why would you be sad that I have so much content? But yeah, anyway I unsubscribed recently, but I'm such a fan. And so I'm so curious, one, how did you connect with him and how did that even happen? And then two, what is he like to work with? Wes Kao (07:37): Both very, very juicy questions. So the way that we connected was Seth had put out a blog post saying that he was looking for a special projects lead to help him figure out what to do next. So this was in 2014 when he had just sold off his last company Squidoo that he had been working on for I think, eight years or so before that. Wes Kao (07:57): So he was ready for something new, at a crossroads, wanted some fresh inspiration, and I saw this blog post on a whim. And at that time I was at that ad tech company in San Francisco and I thought there are probably thousands of people who are going to be applying to this, so I don't want to get my hopes up. I did want to move to New York. I feel like everyone in SF and California at some time wants to move to New York. And so I thought, all right, I'm going to toss my hat in the ring and not overthink it. Wes Kao (08:25): And so the application required a video, so there was a written application and then there was a video. So Seth said, \"Take three minutes to talk about what you want to build, what you want to contribute, and what you want to learn,\" something along those lines. Wes Kao (08:39): And I did my video in one take. Normally I would've done multiple takes for sure, but here I just thought there's a very little chance I'm going to get this. And a couple days later to my surprise, I get an email from Seth Godin. He's in my inbox and I'm just jumping up and down in my living room because he's asked, \"Hey, loved your video. Let's hop on a call for an interview.\" And of course I write a very calm professional response and we did a couple rounds of interviews and I get the role. Wes Kao (09:06): So I pack my life into six suitcases, get an apartment sight unseen in this little town right outside of New York City, where Seth's office is, it's called Hastings-on-Hudson. And what initially started off as a six month role eventually led to over three years working together and starting the altMBA together. Wes Kao (09:24): So that's how we got connected, very serendipitous. But my lesson there is don't take yourself out of the running before you get rejected. Don't reject yourself, basically. I think a lot of us have high standards and high expectations of ourselves and it's almost like, oh, if I can't do the best application, then I just shouldn't apply. If I don't have time to take five takes of this video, it won't be good enough, and so I just shouldn't do it. So for me, that was a great lesson in putting your best foot forward, but putting your foot forward. Lenny (09:55): I love that. Wes Kao (09:57): So that was how we got connected. And then in terms of what it was like working with him, I think the Seth that people know externally can sometimes be different from the behind-the-scenes Seth. And that I think that's true for all of us, by the way. And so I think externally, he can sometimes be a little bit of a vague Buddha, if you will. He gives great inspiring advice. His insights, I think are amazing. Wes Kao (10:22): If you look at his blog, some people try to copy Seth's blog by writing short daily posts, but that is not the reason why Seth's blog is so good. That is incidental, that they are short and daily. The reason why it works is because they are so insight rich. Wes Kao (10:39): And in person, he is even smarter and even sharper than he is in writing and online, which is so amazing. I'm just shocked by that because I feel like most people are the opposite. It's like you have time to curate what goes on your Twitter, your website. You have time to manicure this, what you want people to think of you, but when you are live, you're there with the person, you're talking like normal people and you can really get a sense of how sharp or insightful or genuine someone is. And I think he's even more genuine, even sharper, even funnier in person. Wes Kao (11:12): So that was kind of high level. I think the other thing is that internally we had really high standards for what we would ship, which is a little bit different, I think, than what you might think if you were a Seth reader. Because before I would read him and just do it, essentially, ship, put yourself out there, don't overthink it. Wes Kao (11:34): And you might think that, that means that there's a trade-off with quality, but the thing that I found so surprising about working together was that we often produced work almost always that was high quality, fast, and what's that third thing of that triangle? Cheap, or not cheap, but affordable or economical. Usually it's like, oh, you only get two of these or there's the trade-off between quality and speed, but we worked fast and we produced really great work. Wes Kao (12:06): And so I think for me, it really raised the bar on everything for me and on strategies, on tactics, on expectations, on quality, speed. I think the speed that we shipped ... Before I was at a Sequoia-backed ad tech startup and I thought, oh, I know what shipping fast is, I was at a startup. Wes Kao (12:26): And the speed that we shipped at Seth HQ was just beyond. It just blew away what I think normal people think of as fast, but it was also still so good. And so I think that rigor and that refusal to accept anything but excellence was just so awesome. And it really spoke to me because I care a lot about craft. I think more people should care about craft and I'm also kind of an obsessed person. I have an obsessive personality and I just loved how Seth was similarly obsessed. And so yeah, learned so much from him that I've taken with me obviously in building Maven now and everything that I do. Lenny (13:12): Wow. I've 10 more questions I'd love to ask about Seth Godin, but I should probably try to get him on the podcast. What a coup that would be. I have a sad story actually. I just remembered while you were talking, I saw him mentioned once that he replies to every email he gets. And so I emailed him because- Wes Kao (13:30): Just to check. Lenny (13:31): ... I had such a crush. Yeah, just to test. And he replied and he's like, \"Why would I say this if I wasn't doing this? What benefit would that be for me?\" I was like, \"Oh shit, I pissed him off. Wes Kao (13:40): So funny. Lenny (13:40): He hates me. Wes Kao (13:43): It's hilarious. Lenny (13:44): Oh man. Okay. Amazing. One last quick question. You also worked with Scott Galloway, who's a very polarizing figure on Twitter at least, and you helped him create his courses. Maybe just one quick question on him, what's he like and why do people dislike him so much on Twitter? Wes Kao (14:00): Yeah, I don't know about people disliking him. He definitely has spiky points of view, which I think are amazing. Yeah. So Section4, Scott Galloway's company was one of the first clients that I worked with after leaving altMBA, and I didn't work too closely with Scott. I worked really closely with his CEO, Greg Shove and their exec team to design the sprint that's now their go-to course format. But yeah, I didn't work too closely with him directly. Lenny (14:27): Okay, cool. We won't get too deep there. Okay, so what I want to do with most of the time that we have together is to go into five big ideas. You could call it the five big ideas from Wes Kao, concepts that you've shared in other places that you've touched on your writing and tweeting and things like that have struck and have stuck with me and I suspect many other people, and just go deeper on these ideas. Does that sound good? Wes Kao (14:49): Sounds great. Lenny (14:51): Awesome. So the first idea I want to chat about is something you call the super specific how. And you wrote a post about this and it really clarified a lot of my thinking on writing and the newsletter and the podcast. And I find myself sharing this post and concept with other writers who are struggling a bit with their content. And so can you just explain this idea of the super specific how, and generally just how it can make folks better writers and thinkers? Wes Kao (15:18): Yeah. The idea of the super specific how is that most writers, most course instructors spend too much time on the what and the why and not enough time on how. So if you think about people who are reading your writing, most of them probably already agree with the general premise of what you're saying. Wes Kao (15:44): Unless what you're saying is truly controversial, a ground-breaker, or new to your audience, you don't need to spend too much time elaborating on the concept itself and why it matters. People really want to know how do I do this? How do I apply this to my own life? How do I think about the nuances when I'm applying this? What are examples that I can look at that help me better internalize how this","wordCount":3000}